build_scripts/installer-version.py
mozilla-ca/__init__.py
mozilla-ca/cacert.pem
spare/__init__.py
spare/pyinstaller.spec
spare/cmds/__init__.py
spare/cmds/configure.py
spare/cmds/farm.py
spare/cmds/farm_funcs.py
spare/cmds/init.py
spare/cmds/init_funcs.py
spare/cmds/keys.py
spare/cmds/keys_funcs.py
spare/cmds/netspace.py
spare/cmds/netspace_funcs.py
spare/cmds/plots.py
spare/cmds/show.py
spare/cmds/spare.py
spare/cmds/start.py
spare/cmds/start_funcs.py
spare/cmds/stop.py
spare/cmds/units.py
spare/cmds/wallet.py
spare/cmds/wallet_funcs.py
spare/consensus/__init__.py
spare/consensus/block_body_validation.py
spare/consensus/block_creation.py
spare/consensus/block_header_validation.py
spare/consensus/block_record.py
spare/consensus/block_rewards.py
spare/consensus/block_root_validation.py
spare/consensus/blockchain.py
spare/consensus/blockchain_interface.py
spare/consensus/coinbase.py
spare/consensus/condition_costs.py
spare/consensus/constants.py
spare/consensus/cost_calculator.py
spare/consensus/default_constants.py
spare/consensus/deficit.py
spare/consensus/difficulty_adjustment.py
spare/consensus/find_fork_point.py
spare/consensus/full_block_to_block_record.py
spare/consensus/get_block_challenge.py
spare/consensus/make_sub_epoch_summary.py
spare/consensus/multiprocess_validation.py
spare/consensus/network_type.py
spare/consensus/pos_quality.py
spare/consensus/pot_iterations.py
spare/consensus/vdf_info_computation.py
spare/daemon/__init__.py
spare/daemon/client.py
spare/daemon/server.py
spare/daemon/windows_signal.py
spare/farmer/__init__.py
spare/farmer/farmer.py
spare/farmer/farmer_api.py
spare/full_node/__init__.py
spare/full_node/block_store.py
spare/full_node/bundle_tools.py
spare/full_node/coin_store.py
spare/full_node/full_node.py
spare/full_node/full_node_api.py
spare/full_node/full_node_store.py
spare/full_node/generator.py
spare/full_node/mempool.py
spare/full_node/mempool_check_conditions.py
spare/full_node/mempool_manager.py
spare_blockchain-1.0.3.dist-info/LICENSE
spare_blockchain-1.0.3.dist-info/METADATA
spare_blockchain-1.0.3.dist-info/WHEEL
spare_blockchain-1.0.3.dist-info/entry_points.txt
spare_blockchain-1.0.3.dist-info/top_level.txt
spare_blockchain-1.0.3.dist-info/RECORD
